{"id":"node_modules\\bluebird\\js\\release\\any.js","dependencies":[{"name":"C:\\Users\\arvid\\IdeaProjects\\Shoumi\\node_modules\\bluebird\\package.json","includedInParent":true,"mtime":1534849347949},{"name":"C:\\Users\\arvid\\IdeaProjects\\Shoumi\\package.json","includedInParent":true,"mtime":1537044159153}],"generated":{"js":"\"use strict\";\nmodule.exports = function(Promise) {\nvar SomePromiseArray = Promise._SomePromiseArray;\nfunction any(promises) {\n    var ret = new SomePromiseArray(promises);\n    var promise = ret.promise();\n    ret.setHowMany(1);\n    ret.setUnwrap();\n    ret.init();\n    return promise;\n}\n\nPromise.any = function (promises) {\n    return any(promises);\n};\n\nPromise.prototype.any = function () {\n    return any(this);\n};\n\n};\n","map":{"mappings":[{"source":"node_modules\\bluebird\\js\\release\\any.js","original":{"line":1,"column":0},"generated":{"line":1,"column":0}},{"source":"node_modules\\bluebird\\js\\release\\any.js","original":{"line":2,"column":0},"generated":{"line":2,"column":0}},{"source":"node_modules\\bluebird\\js\\release\\any.js","original":{"line":3,"column":0},"generated":{"line":3,"column":0}},{"source":"node_modules\\bluebird\\js\\release\\any.js","original":{"line":4,"column":0},"generated":{"line":4,"column":0}},{"source":"node_modules\\bluebird\\js\\release\\any.js","original":{"line":5,"column":0},"generated":{"line":5,"column":0}},{"source":"node_modules\\bluebird\\js\\release\\any.js","original":{"line":6,"column":0},"generated":{"line":6,"column":0}},{"source":"node_modules\\bluebird\\js\\release\\any.js","original":{"line":7,"column":0},"generated":{"line":7,"column":0}},{"source":"node_modules\\bluebird\\js\\release\\any.js","original":{"line":8,"column":0},"generated":{"line":8,"column":0}},{"source":"node_modules\\bluebird\\js\\release\\any.js","original":{"line":9,"column":0},"generated":{"line":9,"column":0}},{"source":"node_modules\\bluebird\\js\\release\\any.js","original":{"line":10,"column":0},"generated":{"line":10,"column":0}},{"source":"node_modules\\bluebird\\js\\release\\any.js","original":{"line":11,"column":0},"generated":{"line":11,"column":0}},{"source":"node_modules\\bluebird\\js\\release\\any.js","original":{"line":12,"column":0},"generated":{"line":12,"column":0}},{"source":"node_modules\\bluebird\\js\\release\\any.js","original":{"line":13,"column":0},"generated":{"line":13,"column":0}},{"source":"node_modules\\bluebird\\js\\release\\any.js","original":{"line":14,"column":0},"generated":{"line":14,"column":0}},{"source":"node_modules\\bluebird\\js\\release\\any.js","original":{"line":15,"column":0},"generated":{"line":15,"column":0}},{"source":"node_modules\\bluebird\\js\\release\\any.js","original":{"line":16,"column":0},"generated":{"line":16,"column":0}},{"source":"node_modules\\bluebird\\js\\release\\any.js","original":{"line":17,"column":0},"generated":{"line":17,"column":0}},{"source":"node_modules\\bluebird\\js\\release\\any.js","original":{"line":18,"column":0},"generated":{"line":18,"column":0}},{"source":"node_modules\\bluebird\\js\\release\\any.js","original":{"line":19,"column":0},"generated":{"line":19,"column":0}},{"source":"node_modules\\bluebird\\js\\release\\any.js","original":{"line":20,"column":0},"generated":{"line":20,"column":0}},{"source":"node_modules\\bluebird\\js\\release\\any.js","original":{"line":21,"column":0},"generated":{"line":21,"column":0}},{"source":"node_modules\\bluebird\\js\\release\\any.js","original":{"line":22,"column":0},"generated":{"line":22,"column":0}}],"sources":{"node_modules\\bluebird\\js\\release\\any.js":"\"use strict\";\nmodule.exports = function(Promise) {\nvar SomePromiseArray = Promise._SomePromiseArray;\nfunction any(promises) {\n    var ret = new SomePromiseArray(promises);\n    var promise = ret.promise();\n    ret.setHowMany(1);\n    ret.setUnwrap();\n    ret.init();\n    return promise;\n}\n\nPromise.any = function (promises) {\n    return any(promises);\n};\n\nPromise.prototype.any = function () {\n    return any(this);\n};\n\n};\n"},"lineCount":22}},"hash":"7dc8dfcacd558c665ab4671a85882060","cacheData":{"env":{}}}